MANIFEST.in
README.md
license.txt
setup.py
cogandmem/__init__.py
cogandmem/experiment.py
cogandmem/generic.py
cogandmem/score.py
cogandmem/tetromino.py
cogandmem/text.py
cogandmem/writing.py
cogandmem.egg-info/PKG-INFO
cogandmem.egg-info/SOURCES.txt
cogandmem.egg-info/dependency_links.txt
cogandmem.egg-info/requires.txt
cogandmem.egg-info/top_level.txt
examples/cued recall/.DS_Store
examples/cued recall/Toronto noun pool.txt
examples/cued recall/main.py