Metadata-Version: 2.1
Name: cogandmem
Version: 0.1.0
Summary: Package for running memory experiments
Home-page: https://github.com/TylerEnsor/cogandmem
Author: Tyler M. Ensor
Author-email: tyler.ensor@mun.ca
License: UNKNOWN
Keywords: psychology experiment memory cognition
Platform: UNKNOWN
Classifier: Intended Audience :: Science/Research
Classifier: Programming Language :: Python :: 2
Classifier: Natural Language :: English
Classifier: License :: OSI Approved :: MIT License
